louvain/Optimiser.py
louvain/VertexPartition.py
louvain/__init__.py
louvain/_c_louvain.cpython-37m-darwin.so
louvain/_version.py
louvain/functions.py
louvain_github-0.6.1.post1.dist-info/LICENSE
louvain_github-0.6.1.post1.dist-info/METADATA
louvain_github-0.6.1.post1.dist-info/WHEEL
louvain_github-0.6.1.post1.dist-info/top_level.txt
louvain_github-0.6.1.post1.dist-info/RECORD
