Metadata-Version: 2.1
Name: louvain-github
Version: 0.6.1.post1
Summary: Forked from louvain-igraph (https://github.com/vtraag/louvain-igraph). Publish because its PyPI version is out-of-date, whereas our scCloud package depends on this github repo version. Will remove if a new release is published.
Home-page: https://github.com/vtraag/louvain-igraph
Author: V.A. Traag
Author-email: vincent@traag.net
License: GPLv3+
Platform: UNKNOWN
Classifier: Development Status :: 4 - Beta
Classifier: Environment :: Console
Classifier: Intended Audience :: End Users/Desktop
Classifier: Intended Audience :: Developers
Classifier: Intended Audience :: Science/Research
Classifier: License :: OSI Approved :: GNU General Public License v3 or later (GPLv3+)
Classifier: Operating System :: MacOS :: MacOS X
Classifier: Operating System :: Microsoft :: Windows
Classifier: Operating System :: POSIX
Classifier: Programming Language :: Python
Classifier: Programming Language :: C++
Classifier: Topic :: Scientific/Engineering :: Mathematics
Classifier: Topic :: Scientific/Engineering :: Information Analysis
Classifier: Topic :: Sociology
Provides: louvain
Requires-Dist: python-igraph (>=0.7.1.0)
